mcp_server_gemini_image_generator/__init__.py
mcp_server_gemini_image_generator/prompts.py
mcp_server_gemini_image_generator/server.py
mcp_server_gemini_image_generator/utils.py
mseep_mcp_server_gemini_image_generator-0.1.4.dist-info/licenses/LICENSE
mseep_mcp_server_gemini_image_generator-0.1.4.dist-info/METADATA
mseep_mcp_server_gemini_image_generator-0.1.4.dist-info/WHEEL
mseep_mcp_server_gemini_image_generator-0.1.4.dist-info/entry_points.txt
mseep_mcp_server_gemini_image_generator-0.1.4.dist-info/top_level.txt
mseep_mcp_server_gemini_image_generator-0.1.4.dist-info/RECORD
